cymmm/__init__.py
cymmm/build.py
cymmm/clean.py
cymmm/display.py
cymmm/engineer.py
cymmm/select.py
cymmm/validate.py
cymmm/week.py
cymmm-0.2.8.dist-info/LICENSE
cymmm-0.2.8.dist-info/METADATA
cymmm-0.2.8.dist-info/WHEEL
cymmm-0.2.8.dist-info/top_level.txt
cymmm-0.2.8.dist-info/RECORD
