Metadata-Version: 2.1
Name: cymmm
Version: 0.2.8
Summary: a package for mmm.
Home-page: https://github.com/hammer-mt/VEX-MMM
Author: Michael Taylor
Author-email: gaozhan19930729@gmail.com
License: MIT
Platform: UNKNOWN
Classifier: License :: OSI Approved :: MIT License
Classifier: Programming Language :: Python
Classifier: Programming Language :: Python :: 3
Classifier: Programming Language :: Python :: 3.6
Classifier: Programming Language :: Python :: Implementation :: CPython
Classifier: Programming Language :: Python :: Implementation :: PyPy
Requires-Python: >=3.6.0
License-File: LICENSE
